.VERSION
AUTHORS.rst
CONTRIBUTING.rst
HISTORY.rst
LICENSE
MANIFEST.in
Pipfile
Pipfile.lock
README.rst
USAGE.rst
dev-requirements.txt
requirements.txt
setup.cfg
setup.py
docs/Makefile
docs/authors.rst
docs/conf.py
docs/contributing.rst
docs/history.rst
docs/index.rst
docs/installation.rst
docs/readme.rst
docs/usage.rst
tests/test_wikiseriesarjanlib.py
wikiseriesarjanlib/.VERSION
wikiseriesarjanlib/AUTHORS.rst
wikiseriesarjanlib/CONTRIBUTING.rst
wikiseriesarjanlib/HISTORY.rst
wikiseriesarjanlib/LICENSE
wikiseriesarjanlib/Pipfile
wikiseriesarjanlib/Pipfile.lock
wikiseriesarjanlib/README.rst
wikiseriesarjanlib/USAGE.rst
wikiseriesarjanlib/__init__.py
wikiseriesarjanlib/_version.py
wikiseriesarjanlib/dev-requirements.txt
wikiseriesarjanlib/requirements.txt
wikiseriesarjanlib/wikiseriesarjanlib.py
wikiseriesarjanlib/wikiseriesarjanlibexceptions.py
wikiseriesarjanlib.egg-info/PKG-INFO
wikiseriesarjanlib.egg-info/SOURCES.txt
wikiseriesarjanlib.egg-info/dependency_links.txt
wikiseriesarjanlib.egg-info/not-zip-safe
wikiseriesarjanlib.egg-info/requires.txt
wikiseriesarjanlib.egg-info/top_level.txt