Metadata-Version: 2.1
Name: wikiseriesarjanlib
Version: 0.0.0
Summary: Lib to use Wikipedia to query TV series
Home-page: https://github.com/4rjan/wikiseriesarjanlib
Author: Arjan Houben
Author-email: arjan@houben.es
License: MIT
Keywords: wikiseriesarjanlib
Classifier: Development Status :: 3 - Alpha
Classifier: Intended Audience :: Developers
Classifier: License :: OSI Approved :: MIT License
Classifier: Natural Language :: English
Classifier: Programming Language :: Python :: 3.9
License-File: LICENSE
License-File: AUTHORS.rst
